README.md
setup.py
deezloader/__init__.py
deezloader/__taggers__.py
deezloader/easy_spoty.py
deezloader/exceptions.py
deezloader.egg-info/PKG-INFO
deezloader.egg-info/SOURCES.txt
deezloader.egg-info/dependency_links.txt
deezloader.egg-info/requires.txt
deezloader.egg-info/top_level.txt
deezloader/bin/deez-dw.py
deezloader/bin/deez-web.py
deezloader/deezloader/__download__.py
deezloader/deezloader/__download_utils__.py
deezloader/deezloader/__init__.py
deezloader/deezloader/__utils__.py
deezloader/deezloader/dee_api.py
deezloader/deezloader/deegw_api.py
deezloader/deezloader/deezer_settings.py
deezloader/libutils/__init__.py
deezloader/libutils/others_settings.py
deezloader/libutils/utils.py
deezloader/models/__init__.py
deezloader/models/album.py
deezloader/models/playlist.py
deezloader/models/preferences.py
deezloader/models/smart.py
deezloader/models/track.py
deezloader/spotloader/__download__.py
deezloader/spotloader/__init__.py
deezloader/spotloader/__spo_api__.py
deezloader/spotloader/spotify_settings.py