Metadata-Version: 2.1
Name: deezloader
Version: 2022.3.3
Summary: Downloads songs, albums or playlists from deezer
Home-page: https://github.com/An0nimia/deezloader
Author: An0nimia
Author-email: An0nimia@protonmail.com
License: CC BY-NC-SA 4.0
Platform: UNKNOWN
Requires-Python: >=3.9
